{"cameraMode":{"drawMode":0,"name":"Shaded","section":"Shading Mode"},"sceneLighting":true,"audioPlay":false,"sceneViewState":{"m_AlwaysRefresh":false,"showFog":true,"showSkybox":true,"showFlares":true,"showImageEffects":true,"showParticleSystems":true,"showVisualEffectGraphs":true,"m_FxEnabled":true},"in2DMode":false,"pivot":{"x":-6.967469215393066,"y":20.127363204956056,"z":24.269330978393556},"rotation":{"x":-0.051677968353033069,"y":0.7670050263404846,"z":-0.06227104365825653,"w":-0.636524498462677},"size":32.71263885498047,"orthographic":false}